schema_overseer_local/__init__.py
schema_overseer_local/exceptions.py
schema_overseer_local/registry.py
schema_overseer_local/utils.py
schema_overseer_local-0.1.1.dist-info/LICENSE
schema_overseer_local-0.1.1.dist-info/METADATA
schema_overseer_local-0.1.1.dist-info/WHEEL
schema_overseer_local-0.1.1.dist-info/RECORD
