Metadata-Version: 2.1
Name: schema-overseer-local
Version: 0.1.1
Summary: Helper to create a compatibility layer between inputs in different formats and other parts of application.
Home-page: https://github.com/Schema-Overseer/schema-overseer-local
License: MIT
Author: Nik Sergievskii
Author-email: nnonexistent@gmail.com
Requires-Python: >=3.8,<4.0
Classifier: License :: OSI Approved :: MIT License
Classifier: Operating System :: OS Independent
Classifier: Programming Language :: Python :: 3
Classifier: Programming Language :: Python :: 3.8
Classifier: Programming Language :: Python :: 3.9
Classifier: Programming Language :: Python :: 3.10
Classifier: Programming Language :: Python :: 3.11
Classifier: Programming Language :: Python :: 3.12
Requires-Dist: pydantic (>=2.5.3,<3.0.0)
Project-URL: Repository, https://github.com/Schema-Overseer/schema-overseer-local
